poetry_src/__init__.py
poetry_src-0.1.0.dist-info/METADATA
poetry_src-0.1.0.dist-info/WHEEL
poetry_src-0.1.0.dist-info/RECORD
