Metadata-Version: 2.1
Name: poetry_src
Version: 0.1.0
Summary: poetry example
Author: luis salamo
Author-email: lsalamo@gmail.com
Requires-Python: >=3.12,<4.0
Classifier: Programming Language :: Python :: 3
Classifier: Programming Language :: Python :: 3.12
Requires-Dist: requests (>=2.32.3,<3.0.0)
